some_aiohttp_middleware/__init__.py
some_aiohttp_middleware/admin_auth.py
some_aiohttp_middleware/base.py
some_aiohttp_middleware/basic_auth.py
some_aiohttp_middleware/cognito.py
some_aiohttp_middleware/db.py
some_aiohttp_middleware/dynamodb.py
some_aiohttp_middleware/memcached.py
some_aiohttp_middleware/s3.py
some_aiohttp_middleware-0.1.13.dist-info/LICENSE
some_aiohttp_middleware-0.1.13.dist-info/METADATA
some_aiohttp_middleware-0.1.13.dist-info/WHEEL
some_aiohttp_middleware-0.1.13.dist-info/RECORD
